{
  "events": [
    {
      "count": 403,
      "cpu_time_total_us": 534.6279999997715,
      "device_time_total_us": 122.46600000005355,
      "key": "aten::to",
      "self_device_time_total_us": 0.0
    },
    {
      "count": 11,
      "cpu_time_total_us": 9.028999999944403,
      "device_time_total_us": 3.487999999999829,
      "key": "cudaStreamIsCapturing",
      "self_device_time_total_us": 3.487999999999829
    },
    {
      "count": 1,
      "cpu_time_total_us": 60.28800000000001,
      "device_time_total_us": 3.487999999999829,
      "key": "aten::randn",
      "self_device_time_total_us": 0.0
    },
    {
      "count": 4,
      "cpu_time_total_us": 94.16700000003993,
      "device_time_total_us": 13.120000000012169,
      "key": "aten::normal_",
      "self_device_time_total_us": 13.120000000012169
    },
    {
      "count": 4,
      "cpu_time_total_us": 0,
      "device_time_total_us": 13.120000000012169,
      "key": "void at::native::(anonymous namespace)::distribution_elementwise_grid_stride_kernel<float, 4, at::native::templates::cuda::normal_and_transform<c10::BFloat16, float, at::CUDAGeneratorImpl*, at::native::templates::cuda::normal_kernel<at::CUDAGeneratorImpl*>(at::TensorBase const&, double, double, at::CUDAGeneratorImpl*)::{lambda()#1}::operator()() const::{lambda()#4}::operator()() const::{lambda(float)#1}>(at::TensorIteratorBase&, at::CUDAGeneratorImpl*, at::native::templates::cuda::normal_kernel<at::CUDAGeneratorImpl*>(at::TensorBase const&, double, double, at::CUDAGeneratorImpl*)::{lambda()#1}::operator()() const::{lambda()#4}::operator()() const::{lambda(float)#1})::{lambda(curandStatePhilox4_32_10*)#2}, at::native::(anonymous namespace)::distribution_nullary_kernel<c10::BFloat16, float, float4, at::CUDAGeneratorImpl*, at::native::templates::cuda::normal_and_transform<c10::BFloat16, float, at::CUDAGeneratorImpl*, at::native::templates::cuda::normal_kernel<at::CUDAGeneratorImpl*>(at::TensorBase const&, double, double, at::CUDAGeneratorImpl*)::{lambda()#1}::operator()() const::{lambda()#4}::operator()() const::{lambda(float)#1}>(at::TensorIteratorBase&, at::CUDAGeneratorImpl*, at::native::templates::cuda::normal_kernel<at::CUDAGeneratorImpl*>(at::TensorBase const&, double, double, at::CUDAGeneratorImpl*)::{lambda()#1}::operator()() const::{lambda()#4}::operator()() const::{lambda(float)#1})::{lambda(curandStatePhilox4_32_10*)#2}, at::native::templates::cuda::normal_kernel<at::CUDAGeneratorImpl*>(at::TensorBase const&, double, double, at::CUDAGeneratorImpl*)::{lambda()#1}::operator()() const::{lambda()#4}::operator()() const::{lambda(float)#1}>(at::TensorIteratorBase&, at::CUDAGeneratorImpl*, at::native::templates::cuda::normal_and_transform<c10::BFloat16, float, at::CUDAGeneratorImpl*, at::native::templates::cuda::normal_kernel<at::CUDAGeneratorImpl*>(at::TensorBase const&, double, double, at::CUDAGeneratorImpl*)::{lambda()#1}::operator()() const::{lambda()#4}::operator()() const::{lambda(float)#1}>(at::TensorIteratorBase&, at::CUDAGeneratorImpl*, at::native::templates::cuda::normal_kernel<at::CUDAGeneratorImpl*>(at::TensorBase const&, double, double, at::CUDAGeneratorImpl*)::{lambda()#1}::operator()() const::{lambda()#4}::operator()() const::{lambda(float)#1})::{lambda(curandStatePhilox4_32_10*)#2} const&, at::native::templates::cuda::normal_kernel<at::CUDAGeneratorImpl*>(at::TensorBase const&, double, double, at::CUDAGeneratorImpl*)::{lambda()#1}::operator()() const::{lambda()#4}::operator()() const::{lambda(float)#1})::{lambda(int, float)#1}>(long, at::PhiloxCudaState, at::native::templates::cuda::normal_and_transform<c10::BFloat16, float, at::CUDAGeneratorImpl*, at::native::templates::cuda::normal_kernel<at::CUDAGeneratorImpl*>(at::TensorBase const&, double, double, at::CUDAGeneratorImpl*)::{lambda()#1}::operator()() const::{lambda()#4}::operator()() const::{lambda(float)#1}>(at::TensorIteratorBase&, at::CUDAGeneratorImpl*, at::native::templates::cuda::normal_kernel<at::CUDAGeneratorImpl*>(at::TensorBase const&, double, double, at::CUDAGeneratorImpl*)::{lambda()#1}::operator()() const::{lambda()#4}::operator()() const::{lambda(float)#1})::{lambda(curandStatePhilox4_32_10*)#2}, at::native::(anonymous namespace)::distribution_nullary_kernel<c10::BFloat16, float, float4, at::CUDAGeneratorImpl*, at::native::templates::cuda::normal_and_transform<c10::BFloat16, float, at::CUDAGeneratorImpl*, at::native::templates::cuda::normal_kernel<at::CUDAGeneratorImpl*>(at::TensorBase const&, double, double, at::CUDAGeneratorImpl*)::{lambda()#1}::operator()() const::{lambda()#4}::operator()() const::{lambda(float)#1}>(at::TensorIteratorBase&, at::CUDAGeneratorImpl*, at::native::templates::cuda::normal_kernel<at::CUDAGeneratorImpl*>(at::TensorBase const&, double, double, at::CUDAGeneratorImpl*)::{lambda()#1}::operator()() const::{lambda()#4}::operator()() const::{lambda(float)#1})::{lambda(curandStatePhilox4_32_10*)#2}, at::native::templates::cuda::normal_kernel<at::CUDAGeneratorImpl*>(at::TensorBase const&, double, double, at::CUDAGeneratorImpl*)::{lambda()#1}::operator()() const::{lambda()#4}::operator()() const::{lambda(float)#1}>(at::TensorIteratorBase&, at::CUDAGeneratorImpl*, at::native::templates::cuda::normal_and_transform<c10::BFloat16, float, at::CUDAGeneratorImpl*, at::native::templates::cuda::normal_kernel<at::CUDAGeneratorImpl*>(at::TensorBase const&, double, double, at::CUDAGeneratorImpl*)::{lambda()#1}::operator()() const::{lambda()#4}::operator()() const::{lambda(float)#1}>(at::TensorIteratorBase&, at::CUDAGeneratorImpl*, at::native::templates::cuda::normal_kernel<at::CUDAGeneratorImpl*>(at::TensorBase const&, double, double, at::CUDAGeneratorImpl*)::{lambda()#1}::operator()() const::{lambda()#4}::operator()() const::{lambda(float)#1})::{lambda(curandStatePhilox4_32_10*)#2} const&, at::native::templates::cuda::normal_kernel<at::CUDAGeneratorImpl*>(at::TensorBase const&, double, double, at::CUDAGeneratorImpl*)::{lambda()#1}::operator()() const::{lambda()#4}::operator()() const::{lambda(float)#1})::{lambda(int, float)#1})",
      "self_device_time_total_us": 13.120000000012169
    },
    {
      "count": 67,
      "cpu_time_total_us": 1077.1170000002148,
      "device_time_total_us": 422.9489999998393,
      "key": "aten::cat",
      "self_device_time_total_us": 422.9489999998393
    },
    {
      "count": 185,
      "cpu_time_total_us": 0,
      "device_time_total_us": 938.9250000003638,
      "key": "Memcpy DtoD (Device -> Device)",
      "self_device_time_total_us": 938.9250000003638
    },
    {
      "count": 1,
      "cpu_time_total_us": 29.769999999999982,
      "device_time_total_us": 1.4079999999999018,
      "key": "aten::zeros",
      "self_device_time_total_us": 0.0
    },
    {
      "count": 6,
      "cpu_time_total_us": 38.31000000001313,
      "device_time_total_us": 1.4079999999999018,
      "key": "aten::zero_",
      "self_device_time_total_us": 0.0
    },
    {
      "count": 3639,
      "cpu_time_total_us": 17930.28800000019,
      "device_time_total_us": 5204.7479999989955,
      "key": "aten::fill_",
      "self_device_time_total_us": 15.743000000038592
    },
    {
      "count": 13,
      "cpu_time_total_us": 0,
      "device_time_total_us": 15.743000000038592,
      "key": "void at::native::vectorized_elementwise_kernel<2, at::native::FillFunctor<long>, std::array<char*, 1ul> >(int, at::native::FillFunctor<long>, std::array<char*, 1ul>)",
      "self_device_time_total_us": 15.743000000038592
    },
    {
      "count": 261,
      "cpu_time_total_us": 496.74699999996665,
      "device_time_total_us": 16.160000000047148,
      "key": "aten::reshape",
      "self_device_time_total_us": 0.0
    },
    {
      "count": 10,
      "cpu_time_total_us": 708.082000000059,
      "device_time_total_us": 371.0400000000177,
      "key": "aten::conv2d",
      "self_device_time_total_us": 0.0
    },
    {
      "count": 44,
      "cpu_time_total_us": 30816.156000000174,
      "device_time_total_us": 7258.459999999244,
      "key": "aten::convolution",
      "self_device_time_total_us": 0.0
    },
    {
      "count": 44,
      "cpu_time_total_us": 30724.88799999963,
      "device_time_total_us": 7258.459999999244,
      "key": "aten::_convolution",
      "self_device_time_total_us": 0.0
    },
    {
      "count": 36,
      "cpu_time_total_us": 1198.0579999999636,
      "device_time_total_us": 416.09700000007206,
      "key": "aten::cudnn_convolution",
      "self_device_time_total_us": 379.51900000003434
    },
    {
      "count": 10,
      "cpu_time_total_us": 0,
      "device_time_total_us": 61.311000000023796,
      "key": "void cudnn::engines_precompiled::nchwToNhwcKernel<__nv_bfloat16, __nv_bfloat16, float, false, true, (cudnnKernelDataType_t)0>(cudnn::engines_precompiled::nchw2nhwc_params_t<float>, __nv_bfloat16 const*, __nv_bfloat16*)",
      "self_device_time_total_us": 61.311000000023796
    },
    {
      "count": 5,
      "cpu_time_total_us": 0,
      "device_time_total_us": 67.67999999998347,
      "key": "cutlass3x_sm100_tensorop_s128x128x16implicit_gemm_fprop_bf16_bf16_f32_void_bf16_f32_128x128x64_dyn_cga_ndhwc_ndhwc_ndhwc_align8_1sm_relu_valpha",
      "self_device_time_total_us": 67.67999999998347
    },
    {
      "count": 36,
      "cpu_time_total_us": 200.6540000000423,
      "device_time_total_us": 197.02600000010443,
      "key": "aten::add_",
      "self_device_time_total_us": 197.02600000010443
    },
    {
      "count": 5,
      "cpu_time_total_us": 0,
      "device_time_total_us": 68.28799999997818,
      "key": "void cudnn::engines_precompiled::nhwcToNchwKernel<__nv_bfloat16, __nv_bfloat16, float, true, false, (cudnnKernelDataType_t)0>(cudnn::engines_precompiled::nhwc2nchw_params_t<float>, __nv_bfloat16 const*, __nv_bfloat16*)",
      "self_device_time_total_us": 68.28799999997818
    },
    {
      "count": 24,
      "cpu_time_total_us": 0,
      "device_time_total_us": 366.1820000000198,
      "key": "void at::native::elementwise_kernel<128, 4, at::native::gpu_kernel_impl_nocast<at::native::CUDAFunctor_add<c10::BFloat16> >(at::TensorIteratorBase&, at::native::CUDAFunctor_add<c10::BFloat16> const&)::{lambda(int)#1}>(int, at::native::gpu_kernel_impl_nocast<at::native::CUDAFunctor_add<c10::BFloat16> >(at::TensorIteratorBase&, at::native::CUDAFunctor_add<c10::BFloat16> const&)::{lambda(int)#1})",
      "self_device_time_total_us": 366.1820000000198
    },
    {
      "count": 17,
      "cpu_time_total_us": 312.279999999942,
      "device_time_total_us": 19.166999999952623,
      "key": "aten::stack",
      "self_device_time_total_us": 0.0
    },
    {
      "count": 188,
      "cpu_time_total_us": 708.5890000005188,
      "device_time_total_us": 109.21700000002875,
      "key": "aten::flatten",
      "self_device_time_total_us": 0.0
    },
    {
      "count": 73,
      "cpu_time_total_us": 787.031999999981,
      "device_time_total_us": 217.12500000015552,
      "key": "aten::clone",
      "self_device_time_total_us": 0.0
    },
    {
      "count": 4049,
      "cpu_time_total_us": 18922.158999999567,
      "device_time_total_us": 10837.35899999942,
      "key": "aten::copy_",
      "self_device_time_total_us": 10837.35899999942
    },
    {
      "count": 3308,
      "cpu_time_total_us": 0,
      "device_time_total_us": 10160.452999998852,
      "key": "void at::native::elementwise_kernel<128, 4, at::native::gpu_kernel_impl_nocast<at::native::direct_copy_kernel_cuda(at::TensorIteratorBase&)::{lambda()#3}::operator()() const::{lambda()#12}::operator()() const::{lambda(c10::BFloat16)#1}>(at::TensorIteratorBase&, at::native::direct_copy_kernel_cuda(at::TensorIteratorBase&)::{lambda()#3}::operator()() const::{lambda()#12}::operator()() const::{lambda(c10::BFloat16)#1} const&)::{lambda(int)#1}>(int, at::native::gpu_kernel_impl_nocast<at::native::direct_copy_kernel_cuda(at::TensorIteratorBase&)::{lambda()#3}::operator()() const::{lambda()#12}::operator()() const::{lambda(c10::BFloat16)#1}>(at::TensorIteratorBase&, at::native::direct_copy_kernel_cuda(at::TensorIteratorBase&)::{lambda()#3}::operator()() const::{lambda()#12}::operator()() const::{lambda(c10::BFloat16)#1} const&)::{lambda(int)#1})",
      "self_device_time_total_us": 10160.452999998852
    },
    {
      "count": 40,
      "cpu_time_total_us": 408.4729999999063,
      "device_time_total_us": 122.46600000005355,
      "key": "aten::_to_copy",
      "self_device_time_total_us": 0.0
    },
    {
      "count": 25,
      "cpu_time_total_us": 0,
      "device_time_total_us": 85.28200000000606,
      "key": "void at::native::unrolled_elementwise_kernel<at::native::direct_copy_kernel_cuda(at::TensorIteratorBase&)::{lambda()#3}::operator()() const::{lambda()#6}::operator()() const::{lambda(double)#1}, std::array<char*, 2ul>, 4, TrivialOffsetCalculator<1, unsigned int>, TrivialOffsetCalculator<1, unsigned int>, at::native::memory::LoadWithCast<1>, at::native::memory::StoreWithCast<1> >(int, at::native::direct_copy_kernel_cuda(at::TensorIteratorBase&)::{lambda()#3}::operator()() const::{lambda()#6}::operator()() const::{lambda(double)#1}, std::array<char*, 2ul>, TrivialOffsetCalculator<1, unsigned int>, TrivialOffsetCalculator<1, unsigned int>, at::native::memory::LoadWithCast<1>, at::native::memory::StoreWithCast<1>)",
      "self_device_time_total_us": 85.28200000000606
    },
    {
      "count": 10,
      "cpu_time_total_us": 179.74600000009013,
      "device_time_total_us": 12.224000000153865,
      "key": "aten::arange",
      "self_device_time_total_us": 6.112000000076932
    },
    {
      "count": 5,
      "cpu_time_total_us": 0,
      "device_time_total_us": 6.112000000076932,
      "key": "void (anonymous namespace)::elementwise_kernel_with_index<int, at::native::arange_cuda_out(c10::Scalar const&, c10::Scalar const&, c10::Scalar const&, at::Tensor&)::{lambda()#1}::operator()() const::{lambda()#6}::operator()() const::{lambda(long)#1}>(int, at::native::arange_cuda_out(c10::Scalar const&, c10::Scalar const&, c10::Scalar const&, at::Tensor&)::{lambda()#1}::operator()() const::{lambda()#6}::operator()() const::{lambda(long)#1}, function_traits<at::native::arange_cuda_out(c10::Scalar const&, c10::Scalar const&, c10::Scalar const&, at::Tensor&)::{lambda()#1}::operator()() const::{lambda()#6}::operator()() const::{lambda(long)#1}>::result_type*)",
      "self_device_time_total_us": 6.112000000076932
    },
    {
      "count": 37,
      "cpu_time_total_us": 300.5570000000266,
      "device_time_total_us": 113.95500000005222,
      "key": "aten::div",
      "self_device_time_total_us": 113.95500000005222
    },
    {
      "count": 5,
      "cpu_time_total_us": 0,
      "device_time_total_us": 8.160999999999603,
      "key": "void at::native::vectorized_elementwise_kernel<2, at::native::BUnaryFunctor<double, double, double, at::native::binary_internal::MulFunctor<double> >, std::array<char*, 2ul> >(int, at::native::BUnaryFunctor<double, double, double, at::native::binary_internal::MulFunctor<double> >, std::array<char*, 2ul>)",
      "self_device_time_total_us": 8.160999999999603
    },
    {
      "count": 5,
      "cpu_time_total_us": 53.028999999991356,
      "device_time_total_us": 6.721000000004551,
      "key": "aten::neg",
      "self_device_time_total_us": 6.721000000004551
    },
    {
      "count": 5,
      "cpu_time_total_us": 0,
      "device_time_total_us": 6.721000000004551,
      "key": "void at::native::vectorized_elementwise_kernel<2, at::native::neg_kernel_cuda(at::TensorIteratorBase&)::{lambda()#2}::operator()() const::{lambda()#6}::operator()() const::{lambda(double)#1}, std::array<char*, 2ul> >(int, at::native::neg_kernel_cuda(at::TensorIteratorBase&)::{lambda()#2}::operator()() const::{lambda()#6}::operator()() const::{lambda(double)#1}, std::array<char*, 2ul>)",
      "self_device_time_total_us": 6.721000000004551
    },
    {
      "count": 10,
      "cpu_time_total_us": 220.40399999990495,
      "device_time_total_us": 65.37799999980007,
      "key": "aten::pow",
      "self_device_time_total_us": 29.696999999914624
    },
    {
      "count": 5,
      "cpu_time_total_us": 49.84800000000678,
      "device_time_total_us": 5.98399999997082,
      "key": "aten::scalar_tensor",
      "self_device_time_total_us": 0.0
    },
    {
      "count": 5,
      "cpu_time_total_us": 0,
      "device_time_total_us": 29.696999999914624,
      "key": "void at::native::elementwise_kernel<128, 4, at::native::gpu_kernel_impl<at::native::(anonymous namespace)::pow_tensor_tensor_kernel(at::TensorIteratorBase&)::{lambda()#1}::operator()() const::{lambda()#6}::operator()() const::{lambda(double, double)#1}>(at::TensorIteratorBase&, at::native::(anonymous namespace)::pow_tensor_tensor_kernel(at::TensorIteratorBase&)::{lambda()#1}::operator()() const::{lambda()#6}::operator()() const::{lambda(double, double)#1} const&)::{lambda(int)#1}>(int, at::native::gpu_kernel_impl<at::native::(anonymous namespace)::pow_tensor_tensor_kernel(at::TensorIteratorBase&)::{lambda()#1}::operator()() const::{lambda()#6}::operator()() const::{lambda(double, double)#1}>(at::TensorIteratorBase&, at::native::(anonymous namespace)::pow_tensor_tensor_kernel(at::TensorIteratorBase&)::{lambda()#1}::operator()() const::{lambda()#6}::operator()() const::{lambda(double, double)#1} const&)::{lambda(int)#1})",
      "self_device_time_total_us": 29.696999999914624
    },
    {
      "count": 5,
      "cpu_time_total_us": 61.206999999907566,
      "device_time_total_us": 8.319999999995161,
      "key": "aten::outer",
      "self_device_time_total_us": 0.0
    },
    {
      "count": 82,
      "cpu_time_total_us": 555.2869999997101,
      "device_time_total_us": 303.9080000001877,
      "key": "aten::mul",
      "self_device_time_total_us": 303.9080000001877
    },
    {
      "count": 10,
      "cpu_time_total_us": 0,
      "device_time_total_us": 21.089000000024498,
      "key": "void at::native::elementwise_kernel<128, 2, at::native::gpu_kernel_impl_nocast<at::native::BinaryFunctor<double, double, double, at::native::binary_internal::MulFunctor<double> > >(at::TensorIteratorBase&, at::native::BinaryFunctor<double, double, double, at::native::binary_internal::MulFunctor<double> > const&)::{lambda(int)#1}>(int, at::native::gpu_kernel_impl_nocast<at::native::BinaryFunctor<double, double, double, at::native::binary_internal::MulFunctor<double> > >(at::TensorIteratorBase&, at::native::BinaryFunctor<double, double, double, at::native::binary_internal::MulFunctor<double> > const&)::{lambda(int)#1})",
      "self_device_time_total_us": 21.089000000024498
    },
    {
      "count": 5,
      "cpu_time_total_us": 63.38899999997602,
      "device_time_total_us": 22.719999999962965,
      "key": "aten::cos",
      "self_device_time_total_us": 22.719999999962965
    },
    {
      "count": 5,
      "cpu_time_total_us": 0,
      "device_time_total_us": 22.719999999962965,
      "key": "void at::native::vectorized_elementwise_kernel<2, at::native::cos_kernel_cuda(at::TensorIteratorBase&)::{lambda()#2}::operator()() const::{lambda()#1}::operator()() const::{lambda(double)#1}, std::array<char*, 2ul> >(int, at::native::cos_kernel_cuda(at::TensorIteratorBase&)::{lambda()#2}::operator()() const::{lambda()#1}::operator()() const::{lambda(double)#1}, std::array<char*, 2ul>)",
      "self_device_time_total_us": 22.719999999962965
    },
    {
      "count": 5,
      "cpu_time_total_us": 50.29899999999998,
      "device_time_total_us": 22.560000000004948,
      "key": "aten::sin",
      "self_device_time_total_us": 22.560000000004948
    },
    {
      "count": 5,
      "cpu_time_total_us": 0,
      "device_time_total_us": 22.560000000004948,
      "key": "void at::native::vectorized_elementwise_kernel<2, at::native::sin_kernel_cuda(at::TensorIteratorBase&)::{lambda()#2}::operator()() const::{lambda()#1}::operator()() const::{lambda(double)#1}, std::array<char*, 2ul> >(int, at::native::sin_kernel_cuda(at::TensorIteratorBase&)::{lambda()#2}::operator()() const::{lambda()#1}::operator()() const::{lambda(double)#1}, std::array<char*, 2ul>)",
      "self_device_time_total_us": 22.560000000004948
    },
    {
      "count": 5,
      "cpu_time_total_us": 0,
      "device_time_total_us": 7.264000000025135,
      "key": "void at::native::(anonymous namespace)::CatArrayBatchedCopy_alignedK_contig<at::native::(anonymous namespace)::OpaqueType<8u>, unsigned int, 2, 128, 1, 16>(at::native::(anonymous namespace)::OpaqueType<8u>*, at::native::(anonymous namespace)::CatArrInputTensorMetadata<at::native::(anonymous namespace)::OpaqueType<8u>, unsigned int, 128, 1>, at::native::(anonymous namespace)::TensorSizeStride<unsigned int, 4u>, int, unsigned int)",
      "self_device_time_total_us": 7.264000000025135
    },
    {
      "count": 13,
      "cpu_time_total_us": 102.04899999999361,
      "device_time_total_us": 18.943000000023858,
      "key": "aten::type_as",
      "self_device_time_total_us": 0.0
    },
    {
      "count": 10,
      "cpu_time_total_us": 0,
      "device_time_total_us": 32.35200000002351,
      "key": "void at::native::unrolled_elementwise_kernel<at::native::direct_copy_kernel_cuda(at::TensorIteratorBase&)::{lambda()#3}::operator()() const::{lambda()#12}::operator()() const::{lambda(c10::BFloat16)#1}, std::array<char*, 2ul>, 4, TrivialOffsetCalculator<1, unsigned int>, TrivialOffsetCalculator<1, unsigned int>, at::native::memory::LoadWithCast<1>, at::native::memory::StoreWithCast<1> >(int, at::native::direct_copy_kernel_cuda(at::TensorIteratorBase&)::{lambda()#3}::operator()() const::{lambda()#12}::operator()() const::{lambda(c10::BFloat16)#1}, std::array<char*, 2ul>, TrivialOffsetCalculator<1, unsigned int>, TrivialOffsetCalculator<1, unsigned int>, at::native::memory::LoadWithCast<1>, at::native::memory::StoreWithCast<1>)",
      "self_device_time_total_us": 32.35200000002351
    },
    {
      "count": 190,
      "cpu_time_total_us": 6357.637999999735,
      "device_time_total_us": 12996.125999999682,
      "key": "aten::linear",
      "self_device_time_total_us": 0.0
    },
    {
      "count": 630,
      "cpu_time_total_us": 12596.150000000187,
      "device_time_total_us": 69663.87100000001,
      "key": "aten::addmm",
      "self_device_time_total_us": 69663.87100000001
    },
    {
      "count": 5,
      "cpu_time_total_us": 0,
      "device_time_total_us": 17.21600000001399,
      "key": "nvjet_tst_64x8_64x16_4x1_v_bz_bias_TNT",
      "self_device_time_total_us": 17.21600000001399
    },
    {
      "count": 39,
      "cpu_time_total_us": 253.92999999987978,
      "device_time_total_us": 66.10999999994101,
      "key": "aten::silu",
      "self_device_time_total_us": 66.10999999994101
    },
    {
      "count": 20,
      "cpu_time_total_us": 0,
      "device_time_total_us": 66.10999999994101,
      "key": "void at::native::vectorized_elementwise_kernel<4, at::native::(anonymous namespace)::silu_kernel(at::TensorIteratorBase&)::{lambda()#1}::operator()() const::{lambda()#6}::operator()() const::{lambda(c10::BFloat16)#1}, std::array<char*, 2ul> >(int, at::native::(anonymous namespace)::silu_kernel(at::TensorIteratorBase&)::{lambda()#1}::operator()() const::{lambda()#6}::operator()() const::{lambda(c10::BFloat16)#1}, std::array<char*, 2ul>)",
      "self_device_time_total_us": 66.10999999994101
    },
    {
      "count": 5,
      "cpu_time_total_us": 0,
      "device_time_total_us": 71.16799999999239,
      "key": "nvjet_tst_64x8_64x16_2x1_v_bz_splitK_bias_TNT",
      "self_device_time_total_us": 71.16799999999239
    },
    {
      "count": 5,
      "cpu_time_total_us": 0,
      "device_time_total_us": 14.144999999984975,
      "key": "void cublasLt::splitKreduce_kernel<32, 16, int, float, __nv_bfloat16, float, __nv_bfloat16, false, float, __nv_bfloat16, __nv_bfloat16, true, true, false, false>(cublasLt::cublasSplitKParams<float>, float const*, __nv_bfloat16 const*, float*, __nv_bfloat16*, float const*, float const*, __nv_bfloat16 const*, float const*, __nv_bfloat16*, void*, long, float*, int*, float*, float*, float const*, float const*, float const*, float const*, float const*)",
      "self_device_time_total_us": 14.144999999984975
    },
    {
      "count": 5,
      "cpu_time_total_us": 0,
      "device_time_total_us": 287.0109999999513,
      "key": "nvjet_tst_256x8_64x6_4x1_v_bz_bias_TNT",
      "self_device_time_total_us": 287.0109999999513
    },
    {
      "count": 5,
      "cpu_time_total_us": 0,
      "device_time_total_us": 31.199999999964348,
      "key": "void at::native::(anonymous namespace)::CatArrayBatchedCopy_alignedK_contig<at::native::(anonymous namespace)::OpaqueType<2u>, unsigned int, 2, 128, 1, 8>(at::native::(anonymous namespace)::OpaqueType<2u>*, at::native::(anonymous namespace)::CatArrInputTensorMetadata<at::native::(anonymous namespace)::OpaqueType<2u>, unsigned int, 128, 1>, at::native::(anonymous namespace)::TensorSizeStride<unsigned int, 4u>, int, unsigned int)",
      "self_device_time_total_us": 31.199999999964348
    },
    {
      "count": 10,
      "cpu_time_total_us": 0,
      "device_time_total_us": 177.1540000000441,
      "key": "nvjet_tst_144x128_64x8_1x2_2cta_h_bz_bias_TNN",
      "self_device_time_total_us": 177.1540000000441
    },
    {
      "count": 5,
      "cpu_time_total_us": 60.65900000007423,
      "device_time_total_us": 22.144999999979063,
      "key": "aten::gelu",
      "self_device_time_total_us": 22.144999999979063
    },
    {
      "count": 5,
      "cpu_time_total_us": 0,
      "device_time_total_us": 22.144999999979063,
      "key": "void at::native::vectorized_elementwise_kernel<4, at::native::GeluCUDAKernelImpl(at::TensorIteratorBase&, at::native::GeluType)::{lambda()#1}::operator()() const::{lambda()#4}::operator()() const::{lambda(c10::BFloat16)#1}, std::array<char*, 2ul> >(int, at::native::GeluCUDAKernelImpl(at::TensorIteratorBase&, at::native::GeluType)::{lambda()#1}::operator()() const::{lambda()#4}::operator()() const::{lambda(c10::BFloat16)#1}, std::array<char*, 2ul>)",
      "self_device_time_total_us": 22.144999999979063
    },
    {
      "count": 40,
      "cpu_time_total_us": 90379.76499999998,
      "device_time_total_us": 44123.59499999991,
      "key": "Torch-Compiled Region: 0/1",
      "self_device_time_total_us": 0.0
    },
    {
      "count": 200,
      "cpu_time_total_us": 13746.6490000004,
      "device_time_total_us": 4558.09900000006,
      "key": "## Call CompiledFxGraph fuh67mwwyfifvu65poxmdnfvc3zukk5l7ofvfw7wqcnloi5p64op ##",
      "self_device_time_total_us": 0.0
    },
    {
      "count": 200,
      "cpu_time_total_us": 2150.524000000111,
      "device_time_total_us": 383.42800000008265,
      "key": "triton_poi_fused_add_unsqueeze_0",
      "self_device_time_total_us": 383.42800000008265
    },
    {
      "count": 200,
      "cpu_time_total_us": 0,
      "device_time_total_us": 5095.057999999982,
      "key": "## Call CompiledFxGraph fuh67mwwyfifvu65poxmdnfvc3zukk5l7ofvfw7wqcnloi5p64op ##",
      "self_device_time_total_us": 5095.057999999982
    },
    {
      "count": 200,
      "cpu_time_total_us": 0,
      "device_time_total_us": 383.42800000008265,
      "key": "triton_poi_fused_add_unsqueeze_0",
      "self_device_time_total_us": 383.42800000008265
    },
    {
      "count": 200,
      "cpu_time_total_us": 1576.5160000000642,
      "device_time_total_us": 4174.670999999978,
      "key": "triton_red_fused_add_mul_native_layer_norm_split_unsqueeze_view_1",
      "self_device_time_total_us": 4174.670999999978
    },
    {
      "count": 200,
      "cpu_time_total_us": 0,
      "device_time_total_us": 4174.670999999978,
      "key": "triton_red_fused_add_mul_native_layer_norm_split_unsqueeze_view_1",
      "self_device_time_total_us": 4174.670999999978
    },
    {
      "count": 40,
      "cpu_time_total_us": 47484.43699999997,
      "device_time_total_us": 17328.296999999817,
      "key": "Torch-Compiled Region: 1/1",
      "self_device_time_total_us": 0.0
    },
    {
      "count": 40,
      "cpu_time_total_us": 3339.4880000000057,
      "device_time_total_us": 8623.468999999921,
      "key": "## Call CompiledFxGraph fk64ajjwdf2q6mjilnqgjewiklnrsdt2pevlvsuyisl466jtpaa3 ##",
      "self_device_time_total_us": 0.0
    },
    {
      "count": 40,
      "cpu_time_total_us": 0,
      "device_time_total_us": 8754.99499999998,
      "key": "## Call CompiledFxGraph fk64ajjwdf2q6mjilnqgjewiklnrsdt2pevlvsuyisl466jtpaa3 ##",
      "self_device_time_total_us": 8754.99499999998
    },
    {
      "count": 200,
      "cpu_time_total_us": 0,
      "device_time_total_us": 38341.78000000025,
      "key": "nvjet_tst_256x128_64x5_2x1_2cta_v_bz_bias_TNT",
      "self_device_time_total_us": 38341.78000000025
    },
    {
      "count": 200,
      "cpu_time_total_us": 1850.0810000003517,
      "device_time_total_us": 2603.7729999999997,
      "key": "triton_red_fused__to_copy_add_mean_mul_pow_rsqrt_split_view_0",
      "self_device_time_total_us": 2603.7729999999997
    },
    {
      "count": 200,
      "cpu_time_total_us": 1421.1669999999299,
      "device_time_total_us": 2368.9829999998674,
      "key": "triton_red_fused__to_copy_add_mean_mul_pow_rsqrt_split_view_1",
      "self_device_time_total_us": 2368.9829999998674
    },
    {
      "count": 400,
      "cpu_time_total_us": 56851.29100000035,
      "device_time_total_us": 5007.46000000004,
      "key": "Torch-Compiled Region: 3/0",
      "self_device_time_total_us": 0.0
    },
    {
      "count": 400,
      "cpu_time_total_us": 48573.69599999985,
      "device_time_total_us": 5007.46000000004,
      "key": "Torch-Compiled Region: 4/1",
      "self_device_time_total_us": 0.0
    },
    {
      "count": 200,
      "cpu_time_total_us": 0,
      "device_time_total_us": 2603.7729999999997,
      "key": "triton_red_fused__to_copy_add_mean_mul_pow_rsqrt_split_view_0",
      "self_device_time_total_us": 2603.7729999999997
    },
    {
      "count": 200,
      "cpu_time_total_us": 0,
      "device_time_total_us": 2368.9829999998674,
      "key": "triton_red_fused__to_copy_add_mean_mul_pow_rsqrt_split_view_1",
      "self_device_time_total_us": 2368.9829999998674
    },
    {
      "count": 400,
      "cpu_time_total_us": 32752.47800000013,
      "device_time_total_us": 5007.46000000004,
      "key": "Torch-Compiled Region: 7/1",
      "self_device_time_total_us": 0.0
    },
    {
      "count": 400,
      "cpu_time_total_us": 21513.978000000025,
      "device_time_total_us": 5007.46000000004,
      "key": "## Call CompiledFxGraph f4oz2wvcxejxwpdxprvuut3twkm7x5q4nrlvgkq2bxu63do7rkav ##",
      "self_device_time_total_us": 0.0
    },
    {
      "count": 400,
      "cpu_time_total_us": 7589.083000000485,
      "device_time_total_us": 5007.46000000004,
      "key": "rope_fused_3way_kernel_v2_0",
      "self_device_time_total_us": 5007.46000000004
    },
    {
      "count": 400,
      "cpu_time_total_us": 0,
      "device_time_total_us": 5007.46000000004,
      "key": "rope_fused_3way_kernel_v2",
      "self_device_time_total_us": 5007.46000000004
    },
    {
      "count": 400,
      "cpu_time_total_us": 0,
      "device_time_total_us": 5007.46000000004,
      "key": "## Call CompiledFxGraph f4oz2wvcxejxwpdxprvuut3twkm7x5q4nrlvgkq2bxu63do7rkav ##",
      "self_device_time_total_us": 5007.46000000004
    },
    {
      "count": 40,
      "cpu_time_total_us": 35966.998999999974,
      "device_time_total_us": 8196.153999999915,
      "key": "Torch-Compiled Region: 21/0",
      "self_device_time_total_us": 0.0
    },
    {
      "count": 40,
      "cpu_time_total_us": 29209.596999999972,
      "device_time_total_us": 7703.345999999904,
      "key": "Torch-Compiled Region: 22/0",
      "self_device_time_total_us": 0.0
    },
    {
      "count": 40,
      "cpu_time_total_us": 2165.940000000008,
      "device_time_total_us": 650.7280000000055,
      "key": "## Call CompiledFxGraph fz2xsbnhyncv5m3nm7v2bf6vozcxvz5hjd4576llteuddvmlokvy ##",
      "self_device_time_total_us": 0.0
    },
    {
      "count": 40,
      "cpu_time_total_us": 388.70699999996395,
      "device_time_total_us": 285.60300000002644,
      "key": "triton_poi_fused_copy_slice_0",
      "self_device_time_total_us": 285.60300000002644
    },
    {
      "count": 40,
      "cpu_time_total_us": 0,
      "device_time_total_us": 918.3140000000103,
      "key": "## Call CompiledFxGraph fz2xsbnhyncv5m3nm7v2bf6vozcxvz5hjd4576llteuddvmlokvy ##",
      "self_device_time_total_us": 918.3140000000103
    },
    {
      "count": 40,
      "cpu_time_total_us": 0,
      "device_time_total_us": 285.60300000002644,
      "key": "triton_poi_fused_copy_slice_0",
      "self_device_time_total_us": 285.60300000002644
    },
    {
      "count": 40,
      "cpu_time_total_us": 279.920999999953,
      "device_time_total_us": 365.1249999999791,
      "key": "triton_poi_fused_copy_slice_1",
      "self_device_time_total_us": 365.1249999999791
    },
    {
      "count": 40,
      "cpu_time_total_us": 0,
      "device_time_total_us": 365.1249999999791,
      "key": "triton_poi_fused_copy_slice_1",
      "self_device_time_total_us": 365.1249999999791
    },
    {
      "count": 40,
      "cpu_time_total_us": 22022.446000000036,
      "device_time_total_us": 3939.019999999933,
      "key": "Torch-Compiled Region: 23/0",
      "self_device_time_total_us": 0.0
    },
    {
      "count": 40,
      "cpu_time_total_us": 21520.40800000004,
      "device_time_total_us": 3939.019999999933,
      "key": "Torch-Compiled Region: 15/2",
      "self_device_time_total_us": 0.0
    },
    {
      "count": 40,
      "cpu_time_total_us": 2366.5970000000225,
      "device_time_total_us": 92.70999999994456,
      "key": "## Call CompiledFxGraph flkvf5ne2bu3ffol6mg5oy5yoeek4gcwetxkon6q2fpf6sste7zs ##",
      "self_device_time_total_us": 0.0
    },
    {
      "count": 240,
      "cpu_time_total_us": 2043.094000000192,
      "device_time_total_us": 272.31300000013744,
      "key": "triton_per_fused__to_copy_cat_cumsum_new_zeros_0",
      "self_device_time_total_us": 272.31300000013744
    },
    {
      "count": 40,
      "cpu_time_total_us": 0,
      "device_time_total_us": 652.61599999998,
      "key": "## Call CompiledFxGraph flkvf5ne2bu3ffol6mg5oy5yoeek4gcwetxkon6q2fpf6sste7zs ##",
      "self_device_time_total_us": 652.61599999998
    },
    {
      "count": 240,
      "cpu_time_total_us": 0,
      "device_time_total_us": 272.31300000013744,
      "key": "triton_per_fused__to_copy_cat_cumsum_new_zeros_0",
      "self_device_time_total_us": 272.31300000013744
    },
    {
      "count": 40,
      "cpu_time_total_us": 275.3320000000049,
      "device_time_total_us": 46.05199999999604,
      "key": "triton_per_fused__to_copy_cat_cumsum_new_zeros_scalar_tensor_stack_1",
      "self_device_time_total_us": 46.05199999999604
    },
    {
      "count": 40,
      "cpu_time_total_us": 0,
      "device_time_total_us": 46.05199999999604,
      "key": "triton_per_fused__to_copy_cat_cumsum_new_zeros_scalar_tensor_stack_1",
      "self_device_time_total_us": 46.05199999999604
    },
    {
      "count": 240,
      "cpu_time_total_us": 71209.5399999999,
      "device_time_total_us": 10681.132000000005,
      "key": "FlashAttnVarlenFunc",
      "self_device_time_total_us": 10681.132000000005
    },
    {
      "count": 240,
      "cpu_time_total_us": 0,
      "device_time_total_us": 10681.132000000005,
      "key": "kernel_cutlass_kernel_flash_attncuteflash_fwd_sm100FlashAttentionForwardSm100_object_at__tensor000o111012_tensor000o111012_tensor000o101112_tensorptrbf16gmemalign16odiv81div8_None_tensorp_0",
      "self_device_time_total_us": 10681.132000000005
    },
    {
      "count": 40,
      "cpu_time_total_us": 3154.818000000014,
      "device_time_total_us": 3113.5979999999654,
      "key": "Torch-Compiled Region: 24/0",
      "self_device_time_total_us": 0.0
    },
    {
      "count": 240,
      "cpu_time_total_us": 12442.88100000014,
      "device_time_total_us": 18325.965000000087,
      "key": "## Call CompiledFxGraph fcceaggubatdtr6yp77cg7bal2pxb7hmqu76agprelqh5hx5asm4 ##",
      "self_device_time_total_us": 0.0
    },
    {
      "count": 400,
      "cpu_time_total_us": 0,
      "device_time_total_us": 30712.93299999976,
      "key": "nvjet_tst_256x128_64x5_2x2_2cta_h_bz_bias_TNT",
      "self_device_time_total_us": 30712.93299999976
    },
    {
      "count": 240,
      "cpu_time_total_us": 0,
      "device_time_total_us": 18325.965000000087,
      "key": "## Call CompiledFxGraph fcceaggubatdtr6yp77cg7bal2pxb7hmqu76agprelqh5hx5asm4 ##",
      "self_device_time_total_us": 18325.965000000087
    },
    {
      "count": 200,
      "cpu_time_total_us": 194412.66499999998,
      "device_time_total_us": 129331.53199999998,
      "key": "Torch-Compiled Region: 13/1",
      "self_device_time_total_us": 0.0
    },
    {
      "count": 200,
      "cpu_time_total_us": 12697.297999999724,
      "device_time_total_us": 5488.372000000478,
      "key": "## Call CompiledFxGraph f732rfwuj3e43dof7xqnzwq6bnjpadzz7val5ryx64zqiuudjyof ##",
      "self_device_time_total_us": 0.0
    },
    {
      "count": 400,
      "cpu_time_total_us": 5921.166999999479,
      "device_time_total_us": 10575.088000000616,
      "key": "triton_red_fused_add_mul_native_layer_norm_view_0",
      "self_device_time_total_us": 10575.088000000616
    },
    {
      "count": 400,
      "cpu_time_total_us": 0,
      "device_time_total_us": 10575.088000000616,
      "key": "triton_red_fused_add_mul_native_layer_norm_view_0",
      "self_device_time_total_us": 10575.088000000616
    },
    {
      "count": 200,
      "cpu_time_total_us": 0,
      "device_time_total_us": 5488.372000000478,
      "key": "## Call CompiledFxGraph f732rfwuj3e43dof7xqnzwq6bnjpadzz7val5ryx64zqiuudjyof ##",
      "self_device_time_total_us": 5488.372000000478
    },
    {
      "count": 200,
      "cpu_time_total_us": 138902.09400000016,
      "device_time_total_us": 40972.980999999985,
      "key": "Torch-Compiled Region: 14/1",
      "self_device_time_total_us": 0.0
    },
    {
      "count": 200,
      "cpu_time_total_us": 13661.026999999918,
      "device_time_total_us": 18471.56399999947,
      "key": "## Call CompiledFxGraph ffw4q4kngccow57pa2mkgee77ogpi55si5mvf26jkdld7scmyvs7 ##",
      "self_device_time_total_us": 0.0
    },
    {
      "count": 600,
      "cpu_time_total_us": 7450.146000000012,
      "device_time_total_us": 84583.19399999974,
      "key": "aten::mm",
      "self_device_time_total_us": 84583.19399999974
    },
    {
      "count": 200,
      "cpu_time_total_us": 0,
      "device_time_total_us": 18855.512999999875,
      "key": "## Call CompiledFxGraph ffw4q4kngccow57pa2mkgee77ogpi55si5mvf26jkdld7scmyvs7 ##",
      "self_device_time_total_us": 18855.512999999875
    },
    {
      "count": 200,
      "cpu_time_total_us": 0,
      "device_time_total_us": 15803.540999999814,
      "key": "nvjet_tst_256x128_64x5_2x2_2cta_h_bz_TNT",
      "self_device_time_total_us": 15803.540999999814
    },
    {
      "count": 200,
      "cpu_time_total_us": 2091.334999999799,
      "device_time_total_us": 2668.0229999996573,
      "key": "triton_red_fused__to_copy_add_addmm_mean_mul_pow_rsqrt_view_0",
      "self_device_time_total_us": 2668.0229999996573
    },
    {
      "count": 200,
      "cpu_time_total_us": 99778.20299999992,
      "device_time_total_us": 7289.050000000397,
      "key": "Torch-Compiled Region: 15/1",
      "self_device_time_total_us": 0.0
    },
    {
      "count": 200,
      "cpu_time_total_us": 0,
      "device_time_total_us": 2668.0229999996573,
      "key": "triton_red_fused__to_copy_add_addmm_mean_mul_pow_rsqrt_view_0",
      "self_device_time_total_us": 2668.0229999996573
    },
    {
      "count": 200,
      "cpu_time_total_us": 11461.787999999608,
      "device_time_total_us": 454.22800000038114,
      "key": "## Call CompiledFxGraph fy2diovumaytikxgbn47fhbd5ncpe2aly5adrlxorw2ifhz2izcc ##",
      "self_device_time_total_us": 0.0
    },
    {
      "count": 200,
      "cpu_time_total_us": 0,
      "device_time_total_us": 1199.2020000001312,
      "key": "## Call CompiledFxGraph fy2diovumaytikxgbn47fhbd5ncpe2aly5adrlxorw2ifhz2izcc ##",
      "self_device_time_total_us": 1199.2020000001312
    },
    {
      "count": 200,
      "cpu_time_total_us": 1252.6169999998883,
      "device_time_total_us": 228.57300000019222,
      "key": "triton_per_fused__to_copy_cat_cumsum_new_zeros_1",
      "self_device_time_total_us": 228.57300000019222
    },
    {
      "count": 200,
      "cpu_time_total_us": 0,
      "device_time_total_us": 228.57300000019222,
      "key": "triton_per_fused__to_copy_cat_cumsum_new_zeros_1",
      "self_device_time_total_us": 228.57300000019222
    },
    {
      "count": 200,
      "cpu_time_total_us": 15746.734999999546,
      "device_time_total_us": 15212.367000000122,
      "key": "Torch-Compiled Region: 18/0",
      "self_device_time_total_us": 0.0
    },
    {
      "count": 200,
      "cpu_time_total_us": 29944.77900000035,
      "device_time_total_us": 82870.17899999951,
      "key": "Torch-Compiled Region: 19/0",
      "self_device_time_total_us": 0.0
    },
    {
      "count": 200,
      "cpu_time_total_us": 24068.011000000035,
      "device_time_total_us": 82870.17899999951,
      "key": "## Call CompiledFxGraph fzkr5p2ai4jlimh5nkeoy4kj6gag3djpy7rrfhfz6gvfo74pftp2 ##",
      "self_device_time_total_us": 0.0
    },
    {
      "count": 200,
      "cpu_time_total_us": 0,
      "device_time_total_us": 84514.77699999991,
      "key": "## Call CompiledFxGraph fzkr5p2ai4jlimh5nkeoy4kj6gag3djpy7rrfhfz6gvfo74pftp2 ##",
      "self_device_time_total_us": 84514.77699999991
    },
    {
      "count": 200,
      "cpu_time_total_us": 0,
      "device_time_total_us": 34113.5329999996,
      "key": "nvjet_tst_128x256_64x6_2x1_2cta_v_bz_TNT",
      "self_device_time_total_us": 34113.5329999996
    },
    {
      "count": 200,
      "cpu_time_total_us": 1772.2059999999756,
      "device_time_total_us": 6798.8819999996595,
      "key": "triton_poi_fused_addmm_gelu_view_1",
      "self_device_time_total_us": 6798.8819999996595
    },
    {
      "count": 200,
      "cpu_time_total_us": 1756.9080000001768,
      "device_time_total_us": 2204.9279999997907,
      "key": "triton_poi_fused_add_addmm_mul_view_2",
      "self_device_time_total_us": 2204.9279999997907
    },
    {
      "count": 200,
      "cpu_time_total_us": 0,
      "device_time_total_us": 6798.8819999996595,
      "key": "triton_poi_fused_addmm_gelu_view_1",
      "self_device_time_total_us": 6798.8819999996595
    },
    {
      "count": 200,
      "cpu_time_total_us": 0,
      "device_time_total_us": 34666.12000000032,
      "key": "nvjet_tst_256x160_64x5_2x1_2cta_v_bz_TNT",
      "self_device_time_total_us": 34666.12000000032
    },
    {
      "count": 200,
      "cpu_time_total_us": 0,
      "device_time_total_us": 2204.9279999997907,
      "key": "triton_poi_fused_add_addmm_mul_view_2",
      "self_device_time_total_us": 2204.9279999997907
    },
    {
      "count": 65,
      "cpu_time_total_us": 475.718000000139,
      "device_time_total_us": 241.5750000000262,
      "key": "aten::add",
      "self_device_time_total_us": 241.5750000000262
    },
    {
      "count": 5,
      "cpu_time_total_us": 133.36699999999837,
      "device_time_total_us": 86.17699999998149,
      "key": "aten::layer_norm",
      "self_device_time_total_us": 0.0
    },
    {
      "count": 5,
      "cpu_time_total_us": 119.1880000000092,
      "device_time_total_us": 86.17699999998149,
      "key": "aten::native_layer_norm",
      "self_device_time_total_us": 86.17699999998149
    },
    {
      "count": 5,
      "cpu_time_total_us": 0,
      "device_time_total_us": 86.17699999998149,
      "key": "void at::native::(anonymous namespace)::vectorized_layer_norm_kernel<c10::BFloat16, float, false>(int, float, c10::BFloat16 const*, c10::BFloat16 const*, c10::BFloat16 const*, float*, float*, c10::BFloat16*)",
      "self_device_time_total_us": 86.17699999998149
    },
    {
      "count": 5,
      "cpu_time_total_us": 0,
      "device_time_total_us": 12.224000000045635,
      "key": "void at::native::elementwise_kernel<128, 4, at::native::gpu_kernel_impl_nocast<at::native::CUDAFunctorOnSelf_add<c10::BFloat16> >(at::TensorIteratorBase&, at::native::CUDAFunctorOnSelf_add<c10::BFloat16> const&)::{lambda(int)#1}>(int, at::native::gpu_kernel_impl_nocast<at::native::CUDAFunctorOnSelf_add<c10::BFloat16> >(at::TensorIteratorBase&, at::native::CUDAFunctorOnSelf_add<c10::BFloat16> const&)::{lambda(int)#1})",
      "self_device_time_total_us": 12.224000000045635
    },
    {
      "count": 16,
      "cpu_time_total_us": 0,
      "device_time_total_us": 221.4419999999809,
      "key": "void at::native::elementwise_kernel<128, 4, at::native::gpu_kernel_impl_nocast<at::native::BinaryFunctor<c10::BFloat16, c10::BFloat16, c10::BFloat16, at::native::binary_internal::MulFunctor<float> > >(at::TensorIteratorBase&, at::native::BinaryFunctor<c10::BFloat16, c10::BFloat16, c10::BFloat16, at::native::binary_internal::MulFunctor<float> > const&)::{lambda(int)#1}>(int, at::native::gpu_kernel_impl_nocast<at::native::BinaryFunctor<c10::BFloat16, c10::BFloat16, c10::BFloat16, at::native::binary_internal::MulFunctor<float> > >(at::TensorIteratorBase&, at::native::BinaryFunctor<c10::BFloat16, c10::BFloat16, c10::BFloat16, at::native::binary_internal::MulFunctor<float> > const&)::{lambda(int)#1})",
      "self_device_time_total_us": 221.4419999999809
    },
    {
      "count": 5,
      "cpu_time_total_us": 0,
      "device_time_total_us": 42.46400000002177,
      "key": "nvjet_tst_16x64_64x16_2x1_v_bz_bias_TNN",
      "self_device_time_total_us": 42.46400000002177
    },
    {
      "count": 496,
      "cpu_time_total_us": 1013.8519999990094,
      "device_time_total_us": 44.18900000001304,
      "key": "aten::sub",
      "self_device_time_total_us": 44.18900000001304
    },
    {
      "count": 5,
      "cpu_time_total_us": 0,
      "device_time_total_us": 16.926000000021304,
      "key": "void at::native::elementwise_kernel<128, 4, at::native::gpu_kernel_impl<at::native::CUDAFunctor_add<double> >(at::TensorIteratorBase&, at::native::CUDAFunctor_add<double> const&)::{lambda(int)#1}>(int, at::native::gpu_kernel_impl<at::native::CUDAFunctor_add<double> >(at::TensorIteratorBase&, at::native::CUDAFunctor_add<double> const&)::{lambda(int)#1})",
      "self_device_time_total_us": 16.926000000021304
    },
    {
      "count": 16,
      "cpu_time_total_us": 203.85500000002503,
      "device_time_total_us": 24.38399999999092,
      "key": "aten::abs",
      "self_device_time_total_us": 12.19199999999546
    },
    {
      "count": 5,
      "cpu_time_total_us": 0,
      "device_time_total_us": 7.968000000008033,
      "key": "void at::native::vectorized_elementwise_kernel<2, at::native::AbsFunctor<double>, std::array<char*, 2ul> >(int, at::native::AbsFunctor<double>, std::array<char*, 2ul>)",
      "self_device_time_total_us": 7.968000000008033
    },
    {
      "count": 8,
      "cpu_time_total_us": 107.48800000007031,
      "device_time_total_us": 47.32899999998335,
      "key": "aten::argmin",
      "self_device_time_total_us": 47.32899999998335
    },
    {
      "count": 5,
      "cpu_time_total_us": 0,
      "device_time_total_us": 35.7439999999915,
      "key": "void at::native::reduce_kernel<512, 1, at::native::ReduceOp<double, at::native::ArgMinOps<double>, unsigned int, long, 4, 4> >(at::native::ReduceOp<double, at::native::ArgMinOps<double>, unsigned int, long, 4, 4>)",
      "self_device_time_total_us": 35.7439999999915
    },
    {
      "count": 8,
      "cpu_time_total_us": 132.42699999987963,
      "device_time_total_us": 23.10399999996298,
      "key": "aten::index",
      "self_device_time_total_us": 23.10399999996298
    },
    {
      "count": 5,
      "cpu_time_total_us": 0,
      "device_time_total_us": 14.623999999952503,
      "key": "void at::native::index_elementwise_kernel<128, 4, at::native::gpu_index_kernel<at::native::index_kernel_impl<at::native::OpaqueType<8> >(at::TensorIteratorBase&, c10::ArrayRef<long>, c10::ArrayRef<long>)::{lambda(char*, char const*, long)#1}>(at::TensorIteratorBase&, c10::ArrayRef<long>, c10::ArrayRef<long>, at::native::index_kernel_impl<at::native::OpaqueType<8> >(at::TensorIteratorBase&, c10::ArrayRef<long>, c10::ArrayRef<long>)::{lambda(char*, char const*, long)#1} const&, bool)::{lambda(int)#1}>(long, at::native::gpu_index_kernel<at::native::index_kernel_impl<at::native::OpaqueType<8> >(at::TensorIteratorBase&, c10::ArrayRef<long>, c10::ArrayRef<long>)::{lambda(char*, char const*, long)#1}>(at::TensorIteratorBase&, c10::ArrayRef<long>, c10::ArrayRef<long>, at::native::index_kernel_impl<at::native::OpaqueType<8> >(at::TensorIteratorBase&, c10::ArrayRef<long>, c10::ArrayRef<long>)::{lambda(char*, char const*, long)#1} const&, bool)::{lambda(int)#1})",
      "self_device_time_total_us": 14.623999999952503
    },
    {
      "count": 5,
      "cpu_time_total_us": 0,
      "device_time_total_us": 12.92799999997078,
      "key": "void at::native::elementwise_kernel<128, 2, at::native::gpu_kernel_impl_nocast<at::native::CUDAFunctor_add<double> >(at::TensorIteratorBase&, at::native::CUDAFunctor_add<double> const&)::{lambda(int)#1}>(int, at::native::gpu_kernel_impl_nocast<at::native::CUDAFunctor_add<double> >(at::TensorIteratorBase&, at::native::CUDAFunctor_add<double> const&)::{lambda(int)#1})",
      "self_device_time_total_us": 12.92799999997078
    },
    {
      "count": 160,
      "cpu_time_total_us": 369501.4230000001,
      "device_time_total_us": 196994.5020000004,
      "key": "Torch-Compiled Region: 0/2",
      "self_device_time_total_us": 0.0
    },
    {
      "count": 160,
      "cpu_time_total_us": 191228.49000000051,
      "device_time_total_us": 89900.16900000042,
      "key": "Torch-Compiled Region: 1/2",
      "self_device_time_total_us": 0.0
    },
    {
      "count": 160,
      "cpu_time_total_us": 13091.984999999448,
      "device_time_total_us": 34691.0670000002,
      "key": "## Call CompiledFxGraph fe3p354nzwxb6oufl3yqqnv5n7oj6ozrogyabdrellckb4pv7r4i ##",
      "self_device_time_total_us": 0.0
    },
    {
      "count": 160,
      "cpu_time_total_us": 0,
      "device_time_total_us": 35212.15600000006,
      "key": "## Call CompiledFxGraph fe3p354nzwxb6oufl3yqqnv5n7oj6ozrogyabdrellckb4pv7r4i ##",
      "self_device_time_total_us": 35212.15600000006
    },
    {
      "count": 160,
      "cpu_time_total_us": 145839.43300000014,
      "device_time_total_us": 53168.1010000004,
      "key": "Torch-Compiled Region: 8/1",
      "self_device_time_total_us": 0.0
    },
    {
      "count": 160,
      "cpu_time_total_us": 119026.68299999966,
      "device_time_total_us": 51203.12400000017,
      "key": "Torch-Compiled Region: 9/1",
      "self_device_time_total_us": 33507.393000000244
    },
    {
      "count": 160,
      "cpu_time_total_us": 0,
      "device_time_total_us": 33507.393000000244,
      "key": "kernel_cutlass_kernel_flash_attncuteflash_fwd_sm100FlashAttentionForwardSm100_object_at__tensor0000o11101213_tensor0000o11101213_tensor0000o10111213_tensor0000o11101213_None_None_None_Non_0",
      "self_device_time_total_us": 33507.393000000244
    },
    {
      "count": 3,
      "cpu_time_total_us": 0,
      "device_time_total_us": 9.311000000016065,
      "key": "void at::native::elementwise_kernel<128, 4, at::native::gpu_kernel_impl<at::native::CUDAFunctor_add<float> >(at::TensorIteratorBase&, at::native::CUDAFunctor_add<float> const&)::{lambda(int)#1}>(int, at::native::gpu_kernel_impl<at::native::CUDAFunctor_add<float> >(at::TensorIteratorBase&, at::native::CUDAFunctor_add<float> const&)::{lambda(int)#1})",
      "self_device_time_total_us": 9.311000000016065
    },
    {
      "count": 3,
      "cpu_time_total_us": 0,
      "device_time_total_us": 4.223999999987427,
      "key": "void at::native::vectorized_elementwise_kernel<4, at::native::AbsFunctor<float>, std::array<char*, 2ul> >(int, at::native::AbsFunctor<float>, std::array<char*, 2ul>)",
      "self_device_time_total_us": 4.223999999987427
    },
    {
      "count": 3,
      "cpu_time_total_us": 0,
      "device_time_total_us": 11.584999999991851,
      "key": "void at::native::reduce_kernel<512, 1, at::native::ReduceOp<float, at::native::ArgMinOps<float>, unsigned int, long, 4, 4> >(at::native::ReduceOp<float, at::native::ArgMinOps<float>, unsigned int, long, 4, 4>)",
      "self_device_time_total_us": 11.584999999991851
    },
    {
      "count": 3,
      "cpu_time_total_us": 0,
      "device_time_total_us": 8.480000000010477,
      "key": "void at::native::index_elementwise_kernel<128, 4, at::native::gpu_index_kernel<at::native::index_kernel_impl<at::native::OpaqueType<4> >(at::TensorIteratorBase&, c10::ArrayRef<long>, c10::ArrayRef<long>)::{lambda(char*, char const*, long)#1}>(at::TensorIteratorBase&, c10::ArrayRef<long>, c10::ArrayRef<long>, at::native::index_kernel_impl<at::native::OpaqueType<4> >(at::TensorIteratorBase&, c10::ArrayRef<long>, c10::ArrayRef<long>)::{lambda(char*, char const*, long)#1} const&, bool)::{lambda(int)#1}>(long, at::native::gpu_index_kernel<at::native::index_kernel_impl<at::native::OpaqueType<4> >(at::TensorIteratorBase&, c10::ArrayRef<long>, c10::ArrayRef<long>)::{lambda(char*, char const*, long)#1}>(at::TensorIteratorBase&, c10::ArrayRef<long>, c10::ArrayRef<long>, at::native::index_kernel_impl<at::native::OpaqueType<4> >(at::TensorIteratorBase&, c10::ArrayRef<long>, c10::ArrayRef<long>)::{lambda(char*, char const*, long)#1} const&, bool)::{lambda(int)#1})",
      "self_device_time_total_us": 8.480000000010477
    },
    {
      "count": 3,
      "cpu_time_total_us": 40.31899999998859,
      "device_time_total_us": 5.024000000004889,
      "key": "aten::rsub",
      "self_device_time_total_us": 0.0
    },
    {
      "count": 3,
      "cpu_time_total_us": 0,
      "device_time_total_us": 5.024000000004889,
      "key": "void at::native::vectorized_elementwise_kernel<4, at::native::CUDAFunctorOnOther_add<float>, std::array<char*, 2ul> >(int, at::native::CUDAFunctorOnOther_add<float>, std::array<char*, 2ul>)",
      "self_device_time_total_us": 5.024000000004889
    },
    {
      "count": 6,
      "cpu_time_total_us": 0,
      "device_time_total_us": 24.384000000107335,
      "key": "void at::native::elementwise_kernel<128, 4, at::native::gpu_kernel_impl<at::native::BinaryFunctor<float, float, float, at::native::binary_internal::MulFunctor<float> > >(at::TensorIteratorBase&, at::native::BinaryFunctor<float, float, float, at::native::binary_internal::MulFunctor<float> > const&)::{lambda(int)#1}>(int, at::native::gpu_kernel_impl<at::native::BinaryFunctor<float, float, float, at::native::binary_internal::MulFunctor<float> > >(at::TensorIteratorBase&, at::native::BinaryFunctor<float, float, float, at::native::binary_internal::MulFunctor<float> > const&)::{lambda(int)#1})",
      "self_device_time_total_us": 24.384000000107335
    },
    {
      "count": 3,
      "cpu_time_total_us": 0,
      "device_time_total_us": 5.408000000054017,
      "key": "void at::native::vectorized_elementwise_kernel<4, at::native::CUDAFunctor_add<float>, std::array<char*, 3ul> >(int, at::native::CUDAFunctor_add<float>, std::array<char*, 3ul>)",
      "self_device_time_total_us": 5.408000000054017
    },
    {
      "count": 3,
      "cpu_time_total_us": 0,
      "device_time_total_us": 4.832000000023982,
      "key": "void at::native::vectorized_elementwise_kernel<4, at::native::bfloat16_copy_kernel_cuda(at::TensorIteratorBase&)::{lambda(float)#1}, std::array<char*, 2ul> >(int, at::native::bfloat16_copy_kernel_cuda(at::TensorIteratorBase&)::{lambda(float)#1}, std::array<char*, 2ul>)",
      "self_device_time_total_us": 4.832000000023982
    },
    {
      "count": 30,
      "cpu_time_total_us": 329.9299999999348,
      "device_time_total_us": 39.36200000002282,
      "key": "aten::contiguous",
      "self_device_time_total_us": 0.0
    },
    {
      "count": 1,
      "cpu_time_total_us": 15.099999999976717,
      "device_time_total_us": 2.1120000000228174,
      "key": "aten::reciprocal",
      "self_device_time_total_us": 2.1120000000228174
    },
    {
      "count": 1,
      "cpu_time_total_us": 0,
      "device_time_total_us": 2.1120000000228174,
      "key": "void at::native::vectorized_elementwise_kernel<4, at::native::reciprocal_kernel_cuda(at::TensorIteratorBase&)::{lambda()#1}::operator()() const::{lambda()#6}::operator()() const::{lambda(c10::BFloat16)#1}, std::array<char*, 2ul> >(int, at::native::reciprocal_kernel_cuda(at::TensorIteratorBase&)::{lambda()#1}::operator()() const::{lambda()#6}::operator()() const::{lambda(c10::BFloat16)#1}, std::array<char*, 2ul>)",
      "self_device_time_total_us": 2.1120000000228174
    },
    {
      "count": 12,
      "cpu_time_total_us": 0,
      "device_time_total_us": 36.99300000007497,
      "key": "void at::native::vectorized_elementwise_kernel<4, at::native::AUnaryFunctor<c10::BFloat16, c10::BFloat16, c10::BFloat16, at::native::binary_internal::MulFunctor<float> >, std::array<char*, 2ul> >(int, at::native::AUnaryFunctor<c10::BFloat16, c10::BFloat16, c10::BFloat16, at::native::binary_internal::MulFunctor<float> >, std::array<char*, 2ul>)",
      "self_device_time_total_us": 36.99300000007497
    },
    {
      "count": 12,
      "cpu_time_total_us": 0,
      "device_time_total_us": 105.79400000005262,
      "key": "void at::native::elementwise_kernel<128, 4, at::native::gpu_kernel_impl_nocast<at::native::BinaryFunctor<c10::BFloat16, c10::BFloat16, c10::BFloat16, at::native::binary_internal::DivFunctor<c10::BFloat16> > >(at::TensorIteratorBase&, at::native::BinaryFunctor<c10::BFloat16, c10::BFloat16, c10::BFloat16, at::native::binary_internal::DivFunctor<c10::BFloat16> > const&)::{lambda(int)#1}>(int, at::native::gpu_kernel_impl_nocast<at::native::BinaryFunctor<c10::BFloat16, c10::BFloat16, c10::BFloat16, at::native::binary_internal::DivFunctor<c10::BFloat16> > >(at::TensorIteratorBase&, at::native::BinaryFunctor<c10::BFloat16, c10::BFloat16, c10::BFloat16, at::native::binary_internal::DivFunctor<c10::BFloat16> > const&)::{lambda(int)#1})",
      "self_device_time_total_us": 105.79400000005262
    },
    {
      "count": 34,
      "cpu_time_total_us": 30158.443000000145,
      "device_time_total_us": 6887.419999999227,
      "key": "aten::conv3d",
      "self_device_time_total_us": 0.0
    },
    {
      "count": 1,
      "cpu_time_total_us": 0,
      "device_time_total_us": 3.0080000000307336,
      "key": "nvjet_tst_16x64_64x16_1x2_2cta_h_bz_TNN",
      "self_device_time_total_us": 3.0080000000307336
    },
    {
      "count": 4,
      "cpu_time_total_us": 0,
      "device_time_total_us": 165.05600000009872,
      "key": "cutlass3x_sm100_tensorop_s128x128x16implicit_gemm_fprop_bf16_bf16_f32_void_bf16_f32_128x128x64_dyn_cga_ndhwc_ndhwc_ndhwc_align8_2sm_relu_valpha",
      "self_device_time_total_us": 165.05600000009872
    },
    {
      "count": 30,
      "cpu_time_total_us": 255.0549999998184,
      "device_time_total_us": 103.58600000001024,
      "key": "aten::linalg_vector_norm",
      "self_device_time_total_us": 103.58600000001024
    },
    {
      "count": 5,
      "cpu_time_total_us": 0,
      "device_time_total_us": 21.088999999978114,
      "key": "void at::native::reduce_kernel<512, 1, at::native::ReduceOp<c10::BFloat16, at::native::NormTwoOps<c10::BFloat16, float, c10::BFloat16>, unsigned int, c10::BFloat16, 4, 4> >(at::native::ReduceOp<c10::BFloat16, at::native::NormTwoOps<c10::BFloat16, float, c10::BFloat16>, unsigned int, c10::BFloat16, 4, 4>)",
      "self_device_time_total_us": 21.088999999978114
    },
    {
      "count": 30,
      "cpu_time_total_us": 201.12599999981467,
      "device_time_total_us": 18.400999999954365,
      "key": "aten::clamp_min",
      "self_device_time_total_us": 18.400999999954365
    },
    {
      "count": 11,
      "cpu_time_total_us": 0,
      "device_time_total_us": 18.400999999954365,
      "key": "void at::native::vectorized_elementwise_kernel<4, at::native::(anonymous namespace)::launch_clamp_scalar(at::TensorIteratorBase&, c10::Scalar, c10::Scalar, at::native::detail::ClampLimits)::{lambda()#1}::operator()() const::{lambda()#9}::operator()() const::{lambda(c10::BFloat16)#1}, std::array<char*, 2ul> >(int, at::native::(anonymous namespace)::launch_clamp_scalar(at::TensorIteratorBase&, c10::Scalar, c10::Scalar, at::native::detail::ClampLimits)::{lambda()#1}::operator()() const::{lambda()#9}::operator()() const::{lambda(c10::BFloat16)#1}, std::array<char*, 2ul>)",
      "self_device_time_total_us": 18.400999999954365
    },
    {
      "count": 11,
      "cpu_time_total_us": 0,
      "device_time_total_us": 34.94600000005448,
      "key": "void at::native::vectorized_elementwise_kernel<4, at::native::CUDAFunctorOnSelf_add<c10::BFloat16>, std::array<char*, 2ul> >(int, at::native::CUDAFunctorOnSelf_add<c10::BFloat16>, std::array<char*, 2ul>)",
      "self_device_time_total_us": 34.94600000005448
    },
    {
      "count": 5,
      "cpu_time_total_us": 0,
      "device_time_total_us": 19.840999999956694,
      "key": "void at::native::vectorized_elementwise_kernel<4, at::native::CUDAFunctor_add<c10::BFloat16>, std::array<char*, 3ul> >(int, at::native::CUDAFunctor_add<c10::BFloat16>, std::array<char*, 3ul>)",
      "self_device_time_total_us": 19.840999999956694
    },
    {
      "count": 2,
      "cpu_time_total_us": 0,
      "device_time_total_us": 14.17599999991944,
      "key": "nvjet_tst_192x128_64x6_2x1_2cta_v_bz_TNT",
      "self_device_time_total_us": 14.17599999991944
    },
    {
      "count": 1,
      "cpu_time_total_us": 58.23800000001211,
      "device_time_total_us": 275.6510000000126,
      "key": "aten::scaled_dot_product_attention",
      "self_device_time_total_us": 0.0
    },
    {
      "count": 1,
      "cpu_time_total_us": 44.85900000005495,
      "device_time_total_us": 275.6510000000126,
      "key": "aten::_scaled_dot_product_efficient_attention",
      "self_device_time_total_us": 0.0
    },
    {
      "count": 1,
      "cpu_time_total_us": 31.819000000017695,
      "device_time_total_us": 275.6510000000126,
      "key": "aten::_efficient_attention_forward",
      "self_device_time_total_us": 275.6510000000126
    },
    {
      "count": 1,
      "cpu_time_total_us": 0,
      "device_time_total_us": 275.6510000000126,
      "key": "fmha_cutlassF_bf16_aligned_32x128_gmem_sm80(PyTorchMemEffAttention::AttentionKernel<cutlass::bfloat16_t, cutlass::arch::Sm80, true, 32, 128, 65536, true, true>::Params)",
      "self_device_time_total_us": 275.6510000000126
    },
    {
      "count": 8,
      "cpu_time_total_us": 29093.504000000015,
      "device_time_total_us": 6645.336999999068,
      "key": "aten::slow_conv_dilated3d",
      "self_device_time_total_us": 1456.3320000001113
    },
    {
      "count": 7,
      "cpu_time_total_us": 0,
      "device_time_total_us": 1101.3839999999618,
      "key": "void at::native::vol2col_kernel<c10::BFloat16>(long, c10::BFloat16 const*, int, int, int, int, int, int, int, int, int, int, int, int, int, int, int, int, int, int, c10::BFloat16*)",
      "self_device_time_total_us": 1101.3839999999618
    },
    {
      "count": 7,
      "cpu_time_total_us": 0,
      "device_time_total_us": 354.9480000001495,
      "key": "nvjet_tst_128x192_64x7_2x1_2cta_v_badd_NNT",
      "self_device_time_total_us": 354.9480000001495
    },
    {
      "count": 6,
      "cpu_time_total_us": 0,
      "device_time_total_us": 82.49700000003213,
      "key": "void at::native::reduce_kernel<128, 4, at::native::ReduceOp<c10::BFloat16, at::native::NormTwoOps<c10::BFloat16, float, c10::BFloat16>, unsigned int, c10::BFloat16, 4, 4> >(at::native::ReduceOp<c10::BFloat16, at::native::NormTwoOps<c10::BFloat16, float, c10::BFloat16>, unsigned int, c10::BFloat16, 4, 4>)",
      "self_device_time_total_us": 82.49700000003213
    }
  ],
  "meta": {
    "cudnn_benchmark": false,
    "device_cc": [
      10,
      3
    ],
    "device_name": "NVIDIA B300 SXM6 AC",
    "disable_flex_attention_compile": "1",
    "height": 320,
    "iters": 1,
    "kv_bias_backend": "fa4",
    "kv_cache_attention_bias": 0.3,
    "pre_iters": 1,
    "profiled_wall_time_s": 12.48623824099991,
    "stack_exclude": null,
    "stack_include": [
      "CausalWanSelfAttention"
    ],
    "stack_keys": [
      "aten::copy_"
    ],
    "stack_limit": 12,
    "stack_n": 25,
    "torch_cuda_version": "13.0",
    "torch_version": "2.9.0+cu130",
    "triton_ptxas_path": "/usr/local/cuda-12.9/bin/ptxas",
    "wanvae_stream_decode_mode": "chunk",
    "width": 576,
    "with_stack": true
  },
  "stack_groups": {
    "aten::copy_": [
      {
        "count": 8,
        "cpu_time_total_us": 89.11899999997695,
        "device_time_total_us": 133.4100000000617,
        "self_device_time_total_us": 133.4100000000617,
        "stack": [
          "scope/core/pipelines/krea_realtime_video/modules/causal_model.py(1196): torch_dynamo_resume_in_forward_at_1196",
          "scope/core/pipelines/krea_realtime_video/modules/causal_model.py(1190): torch_dynamo_resume_in_forward_at_1190",
          "scope/core/pipelines/krea_realtime_video/modules/causal_model.py(939): forward",
          "torch/nn/modules/module.py(1779): _call_impl",
          "nn.Module: CausalWanSelfAttention_35",
          "scope/core/pipelines/krea_realtime_video/modules/causal_model.py(1730): forward",
          "torch/nn/modules/module.py(1779): _call_impl",
          "torch/_dynamo/eval_frame.py(791): compile_wrapper",
          "nn.Module: CausalWanAttentionBlock_35",
          "scope/core/pipelines/krea_realtime_video/modules/causal_model.py(2286): _forward_inference",
          "scope/core/pipelines/krea_realtime_video/modules/causal_model.py(2623): forward",
          "torch/nn/modules/module.py(1779): _call_impl",
          "nn.Module: CausalWanModel_0",
          "scope/core/pipelines/wan2_1/components/generator.py(314): _call_model",
          "scope/core/pipelines/wan2_1/components/generator.py(332): forward",
          "torch/nn/modules/module.py(1779): _call_impl",
          "nn.Module: WanDiffusionWrapper_0",
          "scope/core/pipelines/wan2_1/blocks/denoise.py(258): __call__",
          "torch/utils/_contextlib.py(117): decorate_context",
          "scope/core/pipelines/krea_realtime_video/modular_blocks.py(173): __call__",
          "torch/utils/_contextlib.py(117): decorate_context",
          "scope/core/pipelines/krea_realtime_video/pipeline.py(302): _generate",
          "scope/core/pipelines/krea_realtime_video/pipeline.py(296): __call__",
          "profile_krea_pipeline_ops.py(319): main",
          "profile_krea_pipeline_ops.py(575): <module>"
        ]
      },
      {
        "count": 8,
        "cpu_time_total_us": 102.81600000007893,
        "device_time_total_us": 133.31400000001304,
        "self_device_time_total_us": 133.31400000001304,
        "stack": [
          "scope/core/pipelines/krea_realtime_video/modules/causal_model.py(1196): torch_dynamo_resume_in_forward_at_1196",
          "scope/core/pipelines/krea_realtime_video/modules/causal_model.py(1190): torch_dynamo_resume_in_forward_at_1190",
          "scope/core/pipelines/krea_realtime_video/modules/causal_model.py(939): forward",
          "torch/nn/modules/module.py(1779): _call_impl",
          "nn.Module: CausalWanSelfAttention_19",
          "scope/core/pipelines/krea_realtime_video/modules/causal_model.py(1730): forward",
          "torch/nn/modules/module.py(1779): _call_impl",
          "torch/_dynamo/eval_frame.py(791): compile_wrapper",
          "nn.Module: CausalWanAttentionBlock_19",
          "scope/core/pipelines/krea_realtime_video/modules/causal_model.py(2286): _forward_inference",
          "scope/core/pipelines/krea_realtime_video/modules/causal_model.py(2623): forward",
          "torch/nn/modules/module.py(1779): _call_impl",
          "nn.Module: CausalWanModel_0",
          "scope/core/pipelines/wan2_1/components/generator.py(314): _call_model",
          "scope/core/pipelines/wan2_1/components/generator.py(332): forward",
          "torch/nn/modules/module.py(1779): _call_impl",
          "nn.Module: WanDiffusionWrapper_0",
          "scope/core/pipelines/wan2_1/blocks/denoise.py(258): __call__",
          "torch/utils/_contextlib.py(117): decorate_context",
          "scope/core/pipelines/krea_realtime_video/modular_blocks.py(173): __call__",
          "torch/utils/_contextlib.py(117): decorate_context",
          "scope/core/pipelines/krea_realtime_video/pipeline.py(302): _generate",
          "scope/core/pipelines/krea_realtime_video/pipeline.py(296): __call__",
          "profile_krea_pipeline_ops.py(319): main",
          "profile_krea_pipeline_ops.py(575): <module>"
        ]
      },
      {
        "count": 8,
        "cpu_time_total_us": 83.35899999992398,
        "device_time_total_us": 133.21800000000803,
        "self_device_time_total_us": 133.21800000000803,
        "stack": [
          "scope/core/pipelines/krea_realtime_video/modules/causal_model.py(1196): torch_dynamo_resume_in_forward_at_1196",
          "scope/core/pipelines/krea_realtime_video/modules/causal_model.py(1190): torch_dynamo_resume_in_forward_at_1190",
          "scope/core/pipelines/krea_realtime_video/modules/causal_model.py(939): forward",
          "torch/nn/modules/module.py(1779): _call_impl",
          "nn.Module: CausalWanSelfAttention_0",
          "scope/core/pipelines/krea_realtime_video/modules/causal_model.py(1730): forward",
          "torch/nn/modules/module.py(1779): _call_impl",
          "torch/_dynamo/eval_frame.py(791): compile_wrapper",
          "nn.Module: CausalWanAttentionBlock_0",
          "scope/core/pipelines/krea_realtime_video/modules/causal_model.py(2286): _forward_inference",
          "scope/core/pipelines/krea_realtime_video/modules/causal_model.py(2623): forward",
          "torch/nn/modules/module.py(1779): _call_impl",
          "nn.Module: CausalWanModel_0",
          "scope/core/pipelines/wan2_1/components/generator.py(314): _call_model",
          "scope/core/pipelines/wan2_1/components/generator.py(332): forward",
          "torch/nn/modules/module.py(1779): _call_impl",
          "nn.Module: WanDiffusionWrapper_0",
          "scope/core/pipelines/wan2_1/blocks/denoise.py(258): __call__",
          "torch/utils/_contextlib.py(117): decorate_context",
          "scope/core/pipelines/krea_realtime_video/modular_blocks.py(173): __call__",
          "torch/utils/_contextlib.py(117): decorate_context",
          "scope/core/pipelines/krea_realtime_video/pipeline.py(302): _generate",
          "scope/core/pipelines/krea_realtime_video/pipeline.py(296): __call__",
          "profile_krea_pipeline_ops.py(319): main",
          "profile_krea_pipeline_ops.py(575): <module>"
        ]
      },
      {
        "count": 8,
        "cpu_time_total_us": 89.34899999997288,
        "device_time_total_us": 133.18500000001222,
        "self_device_time_total_us": 133.18500000001222,
        "stack": [
          "scope/core/pipelines/krea_realtime_video/modules/causal_model.py(1196): torch_dynamo_resume_in_forward_at_1196",
          "scope/core/pipelines/krea_realtime_video/modules/causal_model.py(1190): torch_dynamo_resume_in_forward_at_1190",
          "scope/core/pipelines/krea_realtime_video/modules/causal_model.py(939): forward",
          "torch/nn/modules/module.py(1779): _call_impl",
          "nn.Module: CausalWanSelfAttention_9",
          "scope/core/pipelines/krea_realtime_video/modules/causal_model.py(1730): forward",
          "torch/nn/modules/module.py(1779): _call_impl",
          "torch/_dynamo/eval_frame.py(791): compile_wrapper",
          "nn.Module: CausalWanAttentionBlock_9",
          "scope/core/pipelines/krea_realtime_video/modules/causal_model.py(2286): _forward_inference",
          "scope/core/pipelines/krea_realtime_video/modules/causal_model.py(2623): forward",
          "torch/nn/modules/module.py(1779): _call_impl",
          "nn.Module: CausalWanModel_0",
          "scope/core/pipelines/wan2_1/components/generator.py(314): _call_model",
          "scope/core/pipelines/wan2_1/components/generator.py(332): forward",
          "torch/nn/modules/module.py(1779): _call_impl",
          "nn.Module: WanDiffusionWrapper_0",
          "scope/core/pipelines/wan2_1/blocks/denoise.py(258): __call__",
          "torch/utils/_contextlib.py(117): decorate_context",
          "scope/core/pipelines/krea_realtime_video/modular_blocks.py(173): __call__",
          "torch/utils/_contextlib.py(117): decorate_context",
          "scope/core/pipelines/krea_realtime_video/pipeline.py(302): _generate",
          "scope/core/pipelines/krea_realtime_video/pipeline.py(296): __call__",
          "profile_krea_pipeline_ops.py(319): main",
          "profile_krea_pipeline_ops.py(575): <module>"
        ]
      },
      {
        "count": 8,
        "cpu_time_total_us": 97.00700000001234,
        "device_time_total_us": 132.99400000006426,
        "self_device_time_total_us": 132.99400000006426,
        "stack": [
          "scope/core/pipelines/krea_realtime_video/modules/causal_model.py(1196): torch_dynamo_resume_in_forward_at_1196",
          "scope/core/pipelines/krea_realtime_video/modules/causal_model.py(1190): torch_dynamo_resume_in_forward_at_1190",
          "scope/core/pipelines/krea_realtime_video/modules/causal_model.py(939): forward",
          "torch/nn/modules/module.py(1779): _call_impl",
          "nn.Module: CausalWanSelfAttention_22",
          "scope/core/pipelines/krea_realtime_video/modules/causal_model.py(1730): forward",
          "torch/nn/modules/module.py(1779): _call_impl",
          "torch/_dynamo/eval_frame.py(791): compile_wrapper",
          "nn.Module: CausalWanAttentionBlock_22",
          "scope/core/pipelines/krea_realtime_video/modules/causal_model.py(2286): _forward_inference",
          "scope/core/pipelines/krea_realtime_video/modules/causal_model.py(2623): forward",
          "torch/nn/modules/module.py(1779): _call_impl",
          "nn.Module: CausalWanModel_0",
          "scope/core/pipelines/wan2_1/components/generator.py(314): _call_model",
          "scope/core/pipelines/wan2_1/components/generator.py(332): forward",
          "torch/nn/modules/module.py(1779): _call_impl",
          "nn.Module: WanDiffusionWrapper_0",
          "scope/core/pipelines/wan2_1/blocks/denoise.py(258): __call__",
          "torch/utils/_contextlib.py(117): decorate_context",
          "scope/core/pipelines/krea_realtime_video/modular_blocks.py(173): __call__",
          "torch/utils/_contextlib.py(117): decorate_context",
          "scope/core/pipelines/krea_realtime_video/pipeline.py(302): _generate",
          "scope/core/pipelines/krea_realtime_video/pipeline.py(296): __call__",
          "profile_krea_pipeline_ops.py(319): main",
          "profile_krea_pipeline_ops.py(575): <module>"
        ]
      },
      {
        "count": 8,
        "cpu_time_total_us": 100.13699999998789,
        "device_time_total_us": 132.99400000006426,
        "self_device_time_total_us": 132.99400000006426,
        "stack": [
          "scope/core/pipelines/krea_realtime_video/modules/causal_model.py(1196): torch_dynamo_resume_in_forward_at_1196",
          "scope/core/pipelines/krea_realtime_video/modules/causal_model.py(1190): torch_dynamo_resume_in_forward_at_1190",
          "scope/core/pipelines/krea_realtime_video/modules/causal_model.py(939): forward",
          "torch/nn/modules/module.py(1779): _call_impl",
          "nn.Module: CausalWanSelfAttention_39",
          "scope/core/pipelines/krea_realtime_video/modules/causal_model.py(1730): forward",
          "torch/nn/modules/module.py(1779): _call_impl",
          "torch/_dynamo/eval_frame.py(791): compile_wrapper",
          "nn.Module: CausalWanAttentionBlock_39",
          "scope/core/pipelines/krea_realtime_video/modules/causal_model.py(2286): _forward_inference",
          "scope/core/pipelines/krea_realtime_video/modules/causal_model.py(2623): forward",
          "torch/nn/modules/module.py(1779): _call_impl",
          "nn.Module: CausalWanModel_0",
          "scope/core/pipelines/wan2_1/components/generator.py(314): _call_model",
          "scope/core/pipelines/wan2_1/components/generator.py(332): forward",
          "torch/nn/modules/module.py(1779): _call_impl",
          "nn.Module: WanDiffusionWrapper_0",
          "scope/core/pipelines/wan2_1/blocks/denoise.py(258): __call__",
          "torch/utils/_contextlib.py(117): decorate_context",
          "scope/core/pipelines/krea_realtime_video/modular_blocks.py(173): __call__",
          "torch/utils/_contextlib.py(117): decorate_context",
          "scope/core/pipelines/krea_realtime_video/pipeline.py(302): _generate",
          "scope/core/pipelines/krea_realtime_video/pipeline.py(296): __call__",
          "profile_krea_pipeline_ops.py(319): main",
          "profile_krea_pipeline_ops.py(575): <module>"
        ]
      },
      {
        "count": 8,
        "cpu_time_total_us": 89.65700000000652,
        "device_time_total_us": 132.96099999998114,
        "self_device_time_total_us": 132.96099999998114,
        "stack": [
          "scope/core/pipelines/krea_realtime_video/modules/causal_model.py(1196): torch_dynamo_resume_in_forward_at_1196",
          "scope/core/pipelines/krea_realtime_video/modules/causal_model.py(1190): torch_dynamo_resume_in_forward_at_1190",
          "scope/core/pipelines/krea_realtime_video/modules/causal_model.py(939): forward",
          "torch/nn/modules/module.py(1779): _call_impl",
          "nn.Module: CausalWanSelfAttention_30",
          "scope/core/pipelines/krea_realtime_video/modules/causal_model.py(1730): forward",
          "torch/nn/modules/module.py(1779): _call_impl",
          "torch/_dynamo/eval_frame.py(791): compile_wrapper",
          "nn.Module: CausalWanAttentionBlock_30",
          "scope/core/pipelines/krea_realtime_video/modules/causal_model.py(2286): _forward_inference",
          "scope/core/pipelines/krea_realtime_video/modules/causal_model.py(2623): forward",
          "torch/nn/modules/module.py(1779): _call_impl",
          "nn.Module: CausalWanModel_0",
          "scope/core/pipelines/wan2_1/components/generator.py(314): _call_model",
          "scope/core/pipelines/wan2_1/components/generator.py(332): forward",
          "torch/nn/modules/module.py(1779): _call_impl",
          "nn.Module: WanDiffusionWrapper_0",
          "scope/core/pipelines/wan2_1/blocks/denoise.py(258): __call__",
          "torch/utils/_contextlib.py(117): decorate_context",
          "scope/core/pipelines/krea_realtime_video/modular_blocks.py(173): __call__",
          "torch/utils/_contextlib.py(117): decorate_context",
          "scope/core/pipelines/krea_realtime_video/pipeline.py(302): _generate",
          "scope/core/pipelines/krea_realtime_video/pipeline.py(296): __call__",
          "profile_krea_pipeline_ops.py(319): main",
          "profile_krea_pipeline_ops.py(575): <module>"
        ]
      },
      {
        "count": 8,
        "cpu_time_total_us": 91.00900000004913,
        "device_time_total_us": 132.9299999999057,
        "self_device_time_total_us": 132.9299999999057,
        "stack": [
          "scope/core/pipelines/krea_realtime_video/modules/causal_model.py(1196): torch_dynamo_resume_in_forward_at_1196",
          "scope/core/pipelines/krea_realtime_video/modules/causal_model.py(1190): torch_dynamo_resume_in_forward_at_1190",
          "scope/core/pipelines/krea_realtime_video/modules/causal_model.py(939): forward",
          "torch/nn/modules/module.py(1779): _call_impl",
          "nn.Module: CausalWanSelfAttention_27",
          "scope/core/pipelines/krea_realtime_video/modules/causal_model.py(1730): forward",
          "torch/nn/modules/module.py(1779): _call_impl",
          "torch/_dynamo/eval_frame.py(791): compile_wrapper",
          "nn.Module: CausalWanAttentionBlock_27",
          "scope/core/pipelines/krea_realtime_video/modules/causal_model.py(2286): _forward_inference",
          "scope/core/pipelines/krea_realtime_video/modules/causal_model.py(2623): forward",
          "torch/nn/modules/module.py(1779): _call_impl",
          "nn.Module: CausalWanModel_0",
          "scope/core/pipelines/wan2_1/components/generator.py(314): _call_model",
          "scope/core/pipelines/wan2_1/components/generator.py(332): forward",
          "torch/nn/modules/module.py(1779): _call_impl",
          "nn.Module: WanDiffusionWrapper_0",
          "scope/core/pipelines/wan2_1/blocks/denoise.py(258): __call__",
          "torch/utils/_contextlib.py(117): decorate_context",
          "scope/core/pipelines/krea_realtime_video/modular_blocks.py(173): __call__",
          "torch/utils/_contextlib.py(117): decorate_context",
          "scope/core/pipelines/krea_realtime_video/pipeline.py(302): _generate",
          "scope/core/pipelines/krea_realtime_video/pipeline.py(296): __call__",
          "profile_krea_pipeline_ops.py(319): main",
          "profile_krea_pipeline_ops.py(575): <module>"
        ]
      },
      {
        "count": 8,
        "cpu_time_total_us": 90.03700000001118,
        "device_time_total_us": 132.86600000003818,
        "self_device_time_total_us": 132.86600000003818,
        "stack": [
          "scope/core/pipelines/krea_realtime_video/modules/causal_model.py(1196): torch_dynamo_resume_in_forward_at_1196",
          "scope/core/pipelines/krea_realtime_video/modules/causal_model.py(1190): torch_dynamo_resume_in_forward_at_1190",
          "scope/core/pipelines/krea_realtime_video/modules/causal_model.py(939): forward",
          "torch/nn/modules/module.py(1779): _call_impl",
          "nn.Module: CausalWanSelfAttention_20",
          "scope/core/pipelines/krea_realtime_video/modules/causal_model.py(1730): forward",
          "torch/nn/modules/module.py(1779): _call_impl",
          "torch/_dynamo/eval_frame.py(791): compile_wrapper",
          "nn.Module: CausalWanAttentionBlock_20",
          "scope/core/pipelines/krea_realtime_video/modules/causal_model.py(2286): _forward_inference",
          "scope/core/pipelines/krea_realtime_video/modules/causal_model.py(2623): forward",
          "torch/nn/modules/module.py(1779): _call_impl",
          "nn.Module: CausalWanModel_0",
          "scope/core/pipelines/wan2_1/components/generator.py(314): _call_model",
          "scope/core/pipelines/wan2_1/components/generator.py(332): forward",
          "torch/nn/modules/module.py(1779): _call_impl",
          "nn.Module: WanDiffusionWrapper_0",
          "scope/core/pipelines/wan2_1/blocks/denoise.py(258): __call__",
          "torch/utils/_contextlib.py(117): decorate_context",
          "scope/core/pipelines/krea_realtime_video/modular_blocks.py(173): __call__",
          "torch/utils/_contextlib.py(117): decorate_context",
          "scope/core/pipelines/krea_realtime_video/pipeline.py(302): _generate",
          "scope/core/pipelines/krea_realtime_video/pipeline.py(296): __call__",
          "profile_krea_pipeline_ops.py(319): main",
          "profile_krea_pipeline_ops.py(575): <module>"
        ]
      },
      {
        "count": 8,
        "cpu_time_total_us": 91.20700000005309,
        "device_time_total_us": 132.79999999993015,
        "self_device_time_total_us": 132.79999999993015,
        "stack": [
          "scope/core/pipelines/krea_realtime_video/modules/causal_model.py(1196): torch_dynamo_resume_in_forward_at_1196",
          "scope/core/pipelines/krea_realtime_video/modules/causal_model.py(1190): torch_dynamo_resume_in_forward_at_1190",
          "scope/core/pipelines/krea_realtime_video/modules/causal_model.py(939): forward",
          "torch/nn/modules/module.py(1779): _call_impl",
          "nn.Module: CausalWanSelfAttention_7",
          "scope/core/pipelines/krea_realtime_video/modules/causal_model.py(1730): forward",
          "torch/nn/modules/module.py(1779): _call_impl",
          "torch/_dynamo/eval_frame.py(791): compile_wrapper",
          "nn.Module: CausalWanAttentionBlock_7",
          "scope/core/pipelines/krea_realtime_video/modules/causal_model.py(2286): _forward_inference",
          "scope/core/pipelines/krea_realtime_video/modules/causal_model.py(2623): forward",
          "torch/nn/modules/module.py(1779): _call_impl",
          "nn.Module: CausalWanModel_0",
          "scope/core/pipelines/wan2_1/components/generator.py(314): _call_model",
          "scope/core/pipelines/wan2_1/components/generator.py(332): forward",
          "torch/nn/modules/module.py(1779): _call_impl",
          "nn.Module: WanDiffusionWrapper_0",
          "scope/core/pipelines/wan2_1/blocks/denoise.py(258): __call__",
          "torch/utils/_contextlib.py(117): decorate_context",
          "scope/core/pipelines/krea_realtime_video/modular_blocks.py(173): __call__",
          "torch/utils/_contextlib.py(117): decorate_context",
          "scope/core/pipelines/krea_realtime_video/pipeline.py(302): _generate",
          "scope/core/pipelines/krea_realtime_video/pipeline.py(296): __call__",
          "profile_krea_pipeline_ops.py(319): main",
          "profile_krea_pipeline_ops.py(575): <module>"
        ]
      },
      {
        "count": 8,
        "cpu_time_total_us": 89.4199999999837,
        "device_time_total_us": 132.77199999998265,
        "self_device_time_total_us": 132.77199999998265,
        "stack": [
          "scope/core/pipelines/krea_realtime_video/modules/causal_model.py(1196): torch_dynamo_resume_in_forward_at_1196",
          "scope/core/pipelines/krea_realtime_video/modules/causal_model.py(1190): torch_dynamo_resume_in_forward_at_1190",
          "scope/core/pipelines/krea_realtime_video/modules/causal_model.py(939): forward",
          "torch/nn/modules/module.py(1779): _call_impl",
          "nn.Module: CausalWanSelfAttention_4",
          "scope/core/pipelines/krea_realtime_video/modules/causal_model.py(1730): forward",
          "torch/nn/modules/module.py(1779): _call_impl",
          "torch/_dynamo/eval_frame.py(791): compile_wrapper",
          "nn.Module: CausalWanAttentionBlock_4",
          "scope/core/pipelines/krea_realtime_video/modules/causal_model.py(2286): _forward_inference",
          "scope/core/pipelines/krea_realtime_video/modules/causal_model.py(2623): forward",
          "torch/nn/modules/module.py(1779): _call_impl",
          "nn.Module: CausalWanModel_0",
          "scope/core/pipelines/wan2_1/components/generator.py(314): _call_model",
          "scope/core/pipelines/wan2_1/components/generator.py(332): forward",
          "torch/nn/modules/module.py(1779): _call_impl",
          "nn.Module: WanDiffusionWrapper_0",
          "scope/core/pipelines/wan2_1/blocks/denoise.py(258): __call__",
          "torch/utils/_contextlib.py(117): decorate_context",
          "scope/core/pipelines/krea_realtime_video/modular_blocks.py(173): __call__",
          "torch/utils/_contextlib.py(117): decorate_context",
          "scope/core/pipelines/krea_realtime_video/pipeline.py(302): _generate",
          "scope/core/pipelines/krea_realtime_video/pipeline.py(296): __call__",
          "profile_krea_pipeline_ops.py(319): main",
          "profile_krea_pipeline_ops.py(575): <module>"
        ]
      },
      {
        "count": 8,
        "cpu_time_total_us": 91.78800000002957,
        "device_time_total_us": 132.67300000003888,
        "self_device_time_total_us": 132.67300000003888,
        "stack": [
          "scope/core/pipelines/krea_realtime_video/modules/causal_model.py(1196): torch_dynamo_resume_in_forward_at_1196",
          "scope/core/pipelines/krea_realtime_video/modules/causal_model.py(1190): torch_dynamo_resume_in_forward_at_1190",
          "scope/core/pipelines/krea_realtime_video/modules/causal_model.py(939): forward",
          "torch/nn/modules/module.py(1779): _call_impl",
          "nn.Module: CausalWanSelfAttention_10",
          "scope/core/pipelines/krea_realtime_video/modules/causal_model.py(1730): forward",
          "torch/nn/modules/module.py(1779): _call_impl",
          "torch/_dynamo/eval_frame.py(791): compile_wrapper",
          "nn.Module: CausalWanAttentionBlock_10",
          "scope/core/pipelines/krea_realtime_video/modules/causal_model.py(2286): _forward_inference",
          "scope/core/pipelines/krea_realtime_video/modules/causal_model.py(2623): forward",
          "torch/nn/modules/module.py(1779): _call_impl",
          "nn.Module: CausalWanModel_0",
          "scope/core/pipelines/wan2_1/components/generator.py(314): _call_model",
          "scope/core/pipelines/wan2_1/components/generator.py(332): forward",
          "torch/nn/modules/module.py(1779): _call_impl",
          "nn.Module: WanDiffusionWrapper_0",
          "scope/core/pipelines/wan2_1/blocks/denoise.py(258): __call__",
          "torch/utils/_contextlib.py(117): decorate_context",
          "scope/core/pipelines/krea_realtime_video/modular_blocks.py(173): __call__",
          "torch/utils/_contextlib.py(117): decorate_context",
          "scope/core/pipelines/krea_realtime_video/pipeline.py(302): _generate",
          "scope/core/pipelines/krea_realtime_video/pipeline.py(296): __call__",
          "profile_krea_pipeline_ops.py(319): main",
          "profile_krea_pipeline_ops.py(575): <module>"
        ]
      }
    ]
  }
}
